{
  "$schema": "https://schema.management.azure.com/schemas/2019-09-01/policyDefinition.json#",
  "name": "custom-defender-for-synapse-ws-audit",
  "properties": {
    "displayName": "[Custom] Defender for SQL (Synapse Workspace) - Resource Level Audit",
    "policyType": "Custom",
    "mode": "All",
    "description": "各 Azure Synapse Analytics ワークスペース（Microsoft.Synapse/workspaces）に対して、Defender for SQL がリソース単位（state: Enabled）で有効化されていることを監査します。",
    "metadata": {
      "version": "1.0.0",
      "category": "Security Center"
    },
    "parameters": {
      "effect": {
        "type": "String",
        "metadata": {
          "displayName": "Effect",
          "description": "AuditIfNotExists または Disabled"
        },
        "allowedValues": ["AuditIfNotExists", "Disabled"],
        "defaultValue": "AuditIfNotExists"
      }
    },
    "policyRule": {
      "if": {
        "field": "type",
        "equals": "Microsoft.Synapse/workspaces"
      },
      "then": {
        "effect": "[parameters('effect')]",
        "details": {
          "type": "Microsoft.Synapse/workspaces/securityAlertPolicies",
          "name": "Default",
          "evaluationDelay": "AfterProvisioning",
          "existenceCondition": {
            "field": "Microsoft.Synapse/workspaces/securityAlertPolicies/state",
            "equals": "Enabled"
          }
        }
      }
    }
  }
}
